{
  "schema_version": 2,
  "id": "topology-first-year-2023-jan-part-1-2",
  "subject": "First Year Topology",
  "subject_tag": "topology-first-year",
  "year": 2023,
  "month": "january",
  "part": 1,
  "pdf_url": "https://gma.math.ufl.edu/wp-content/uploads/sites/130/FY-Topology-2-2023_01.pdf",
  "content": [
    {
      "type": "instructions",
      "text": "Work the following problems and show all work. Support all statements to the best of your ability."
    },
    {
      "type": "problem",
      "problem": {
        "text": "Show that every map \\(f:S^2\\to T\\) of the 2-sphere to the torus \\(T\\) is null-homotopic.",
        "subparts": []
      }
    },
    {
      "type": "problem",
      "problem": {
        "text": "Show that the torus \\(T\\) is not homeomorphic to the surface of genus 2, \\(M_2=T\\mathbin{\\#}T\\).",
        "subparts": []
      }
    },
    {
      "type": "problem",
      "problem": {
        "text": "Show that for every continuous map \\(f:S^1\\to S^1\\) there is \\(n\\in\\mathbb{Z}\\) such that \\(f\\) is homotopic to \\(z^n:S^1\\to S^1\\).",
        "subparts": []
      }
    },
    {
      "type": "problem",
      "problem": {
        "text": "Let \\(X=[-1,1]\\times\\{0\\}\\cup\\{0\\}\\times[-1,1]\\subset\\mathbb{R}\\times\\mathbb{R}\\). Show that every continuous map \\(f:X\\to X\\) has a fixed point.",
        "subparts": []
      }
    },
    {
      "type": "problem",
      "problem": {
        "text": "Let \\(X\\), \\(Y\\), and \\(Z\\) denote the \\(x\\)-axis, the \\(y\\)-axis, and the \\(z\\)-axis in \\(\\mathbb{R}^3\\). Is \\(\\pi_1(A)\\) abelian where",
        "subparts": [
          {
            "label": "(a)",
            "text": "\\(A=\\mathbb{R}^3\\setminus X\\)?",
            "subparts": []
          },
          {
            "label": "(b)",
            "text": "\\(A=\\mathbb{R}^3\\setminus(X\\cup Y)\\)?",
            "subparts": []
          },
          {
            "label": "(c)",
            "text": "\\(A=\\mathbb{R}^3\\setminus(X\\cup Y\\cup Z)\\)?",
            "subparts": []
          }
        ]
      }
    },
    {
      "type": "instructions",
      "text": "Answer the following with complete definitions or statements or proofs."
    },
    {
      "type": "problem",
      "problem": {
        "text": "Show that \\(S^2\\) is not homeomorphic to \\(S^3\\).",
        "subparts": []
      }
    },
    {
      "type": "problem",
      "problem": {
        "text": "State the Borsuk–Ulam Theorem for \\(S^2\\).",
        "subparts": []
      }
    },
    {
      "type": "problem",
      "problem": {
        "text": "Let \\(I=[0,1]\\) and let \\(X=I^I\\) be given the product topology. Is the space \\(X\\)",
        "subparts": [
          {
            "label": "(a)",
            "text": "compact?",
            "subparts": []
          },
          {
            "label": "(b)",
            "text": "metrizable?",
            "subparts": []
          },
          {
            "label": "(c)",
            "text": "separable?",
            "subparts": []
          }
        ]
      }
    },
    {
      "type": "problem",
      "problem": {
        "text": "State the Seifert–van Kampen Theorem. Can it be used to compute \\(\\pi_1(S^1)\\)?",
        "subparts": []
      }
    },
    {
      "type": "problem",
      "problem": {
        "text": "",
        "subparts": [
          {
            "label": "(a)",
            "text": "What are completely regular spaces?",
            "subparts": []
          },
          {
            "label": "(b)",
            "text": "Define the Stone–Čech compactification \\(\\beta X\\) of \\(X\\).",
            "subparts": []
          }
        ]
      }
    }
  ]
}
