{
  "schema_version": 3,
  "id": "algebra-phd-2003-sep",
  "subject": "PhD Algebra",
  "subject_tag": "algebra-phd",
  "year": 2003,
  "month": "september",
  "part": null,
  "pdf_url": "https://gma.math.ufl.edu/wp-content/uploads/sites/130/PhD_Algebra_2003_09.pdf",
  "content": [
    {
      "type": "instructions",
      "text": "Do seven of the following eleven problems. Do not turn in more than seven problems. You must show your work. Answers with no work and/or no explanations will receive no credit. State clearly any theorem you use in your proofs. In the problems, \\(\\mathbb{Z}\\), resp. \\(\\mathbb{Q}\\), \\(\\mathbb{C}\\), is the set of all integers, resp. of all rational numbers, of all complex numbers."
    },
    {
      "type": "problem",
      "problem": {
        "body": [
          {
            "type": "text",
            "text": "Consider the following statement \\(A(P)\\): “If a normal subgroup \\(H\\) of a group \\(G\\) and the quotient \\(G/H\\) both have property \\(P\\), then so does \\(G\\).” Prove or disprove \\(A(P)\\), where"
          }
        ],
        "subparts": [
          {
            "label": "a)",
            "text": "\\(P\\) is “being solvable”;",
            "subparts": []
          },
          {
            "label": "b)",
            "text": "\\(P\\) is “being nilpotent”.",
            "subparts": []
          }
        ]
      }
    },
    {
      "type": "problem",
      "problem": {
        "body": [
          {
            "type": "text",
            "text": "Inside the symmetric group \\(S_7\\), consider the subgroup \\(G\\) generated by the permutations \\((1234567)\\) and \\((235)(476)\\). Let\n\\[\nH=\\langle a,b\\mid a^7=b^3=1,\\ bab^{-1}=a^2\\rangle.\n\\]\nShow that \\(G\\simeq H\\)."
          }
        ],
        "subparts": []
      }
    },
    {
      "type": "problem",
      "problem": {
        "body": [
          {
            "type": "text",
            "text": "Let \\(G\\) be a finite group with exactly one maximal subgroup. Prove that \\(G\\) is cyclic of prime power order."
          }
        ],
        "subparts": []
      }
    },
    {
      "type": "problem",
      "problem": {
        "body": [
          {
            "type": "text",
            "text": "Let \\(F\\) be a finite field of finite cardinality \\(q\\) and \\(n\\) be any natural number. Show that there is at least one irreducible polynomial \\(f\\in F[x]\\) of degree \\(n\\)."
          }
        ],
        "subparts": []
      }
    },
    {
      "type": "problem",
      "problem": {
        "body": [
          {
            "type": "text",
            "text": "Let \\(A\\) be a commutative ring with identity. Suppose that \\(M\\) and \\(N\\) are free \\(A\\)-modules with \\(m\\) and \\(n\\) generators, respectively. Prove that if \\(M\\simeq N\\), then \\(m=n\\)."
          }
        ],
        "subparts": []
      }
    },
    {
      "type": "problem",
      "problem": {
        "body": [],
        "subparts": [
          {
            "label": "a)",
            "text": "Give an example of a projective \\(\\mathbb{Z}\\)-module and an example of an injective \\(\\mathbb{Z}\\)-module.",
            "subparts": []
          },
          {
            "label": "b)",
            "text": "Let \\(A\\) be a finite abelian group considered as a \\(\\mathbb{Z}\\)-module and let \\(I\\) be an injective \\(\\mathbb{Z}\\)-module. Compute \\(A\\otimes_{\\mathbb{Z}} I\\).",
            "subparts": []
          }
        ]
      }
    },
    {
      "type": "problem",
      "problem": {
        "body": [
          {
            "type": "text",
            "text": "Let \\(\\alpha\\in\\mathbb{C}\\) be such that \\([\\mathbb{Q}(\\alpha):\\mathbb{Q}]=2003\\). Let \\(E/\\mathbb{Q}\\) be a normal closure of \\(\\mathbb{Q}(\\alpha)/\\mathbb{Q}\\). Prove that \\([E:\\mathbb{Q}]\\) divides \\(2003!\\)."
          }
        ],
        "subparts": []
      }
    },
    {
      "type": "problem",
      "problem": {
        "body": [
          {
            "type": "text",
            "text": "Let \\(\\xi\\in\\mathbb{C}\\) be a primitive \\(77^{\\mathrm{th}}\\) root of unity in \\(\\mathbb{C}\\), and let \\(F=\\mathbb{Q}(\\xi)\\)."
          }
        ],
        "subparts": [
          {
            "label": "a)",
            "text": "Briefly explain why \\(F/\\mathbb{Q}\\) is a Galois extension, and describe the structure of the Galois group \\(\\operatorname{Aut}_{\\mathbb{Q}}(F)\\).",
            "subparts": []
          },
          {
            "label": "b)",
            "text": "Find the number of subfields of \\(F\\) that are quadratic extensions of \\(\\mathbb{Q}\\).",
            "subparts": []
          }
        ]
      }
    },
    {
      "type": "problem",
      "problem": {
        "body": [
          {
            "type": "text",
            "text": "State and prove the Hilbert Basis Theorem."
          }
        ],
        "subparts": []
      }
    },
    {
      "type": "problem",
      "problem": {
        "body": [
          {
            "type": "text",
            "text": "Let \\(D\\) be a Dedekind domain and \\(F\\) be the group of fractional ideals of \\(D\\). Prove that any nontrivial element in \\(F\\) has infinite order."
          }
        ],
        "subparts": []
      }
    },
    {
      "type": "problem",
      "problem": {
        "body": [
          {
            "type": "text",
            "text": "Let \\(R\\) be a commutative ring with identity such that every element \\(x\\in R\\) satisfies \\(x^{n(x)}=x\\) for some integer \\(n(x)\\geq 1\\) depending on \\(x\\). Prove that the Jacobson radical of \\(R\\) is \\(0\\)."
          }
        ],
        "subparts": []
      }
    }
  ]
}
